urepr/__init__.py
urepr/core.py
urepr-0.0.1.dist-info/LICENSE
urepr-0.0.1.dist-info/METADATA
urepr-0.0.1.dist-info/WHEEL
urepr-0.0.1.dist-info/top_level.txt
urepr-0.0.1.dist-info/RECORD
