Metadata-Version: 2.1
Name: urepr
Version: 0.0.1
Summary: Uncertainty representation
Home-page: https://github.com/j-faria/urepr
Author: João Faria
Author-email: joao.faria@astro.up.pt
License: MIT
Platform: UNKNOWN
Classifier: Programming Language :: Python :: 3
Classifier: License :: OSI Approved :: BSD License
Classifier: Operating System :: OS Independent
